setup.py
genius_cli/__init__.py
genius_cli/blocks.py
genius_cli/client.py
genius_cli/main.py
genius_cli/utils.py
genius_cli2.egg-info/PKG-INFO
genius_cli2.egg-info/SOURCES.txt
genius_cli2.egg-info/dependency_links.txt
genius_cli2.egg-info/entry_points.txt
genius_cli2.egg-info/requires.txt
genius_cli2.egg-info/top_level.txt